keycloak_sync/__init__.py
keycloak_sync/kcctl.py
keycloak_sync/model/__init__.py
keycloak_sync/model/csvloader.py
keycloak_sync/model/googlestorage.py
keycloak_sync/model/kc.py
keycloak_sync/model/kcuser.py
keycloak_sync-1.0.0.dist-info/entry_points.txt
keycloak_sync-1.0.0.dist-info/LICENSE
keycloak_sync-1.0.0.dist-info/WHEEL
keycloak_sync-1.0.0.dist-info/METADATA
keycloak_sync-1.0.0.dist-info/RECORD
