Metadata-Version: 2.1
Name: keycloak-sync
Version: 1.0.0
Summary: keycloak cli tool
Author: Kangyi LI
Author-email: nolankangyi@gmail.com
Requires-Python: >=3.8,<4.0
Classifier: Programming Language :: Python :: 3
Classifier: Programming Language :: Python :: 3.8
Classifier: Programming Language :: Python :: 3.9
Requires-Dist: Cerberus (>=1.3.2,<2.0.0)
Requires-Dist: PyYAML (>=5.3.1,<6.0.0)
Requires-Dist: click (>=7.1.2,<8.0.0)
Requires-Dist: colorama (>=0.4.4,<0.5.0)
Requires-Dist: coloredlogs (>=14.0,<15.0)
Requires-Dist: google-cloud-storage (>=1.34.0,<2.0.0)
Requires-Dist: numpy (==1.18.0)
Requires-Dist: pandas (>=1.1.4,<2.0.0)
Requires-Dist: python-keycloak (>=0.23.0,<0.24.0)
